commflex/__init__.py
commflex/apps.py
commflex/sms/__init__.py
commflex/sms/abstract.py
commflex/sms/factory.py
commflex/sms/retry_client.py
commflex/sms/task.py
commflex/sms/provider/ait.py
commflex/sms/provider/aws.py
commflex/sms/provider/constants.py
django_commflex-1.0.1.dist-info/METADATA
django_commflex-1.0.1.dist-info/WHEEL
django_commflex-1.0.1.dist-info/licenses/AUTHORS.rst
django_commflex-1.0.1.dist-info/licenses/LICENCE
django_commflex-1.0.1.dist-info/RECORD
