Metadata-Version: 2.3
Name: django-commflex
Version: 1.0.1
Summary: Provides flexibility of sending messages across multiple channels
Project-URL: Homepage, https://django-commflex.readthedocs.io/en/latest/index.html
Author-email: Josephat Macharia <josemash4@gmail.com>
License: MIT
License-File: AUTHORS.rst
License-File: LICENCE
Provides-Extra: test
Requires-Dist: black; extra == 'test'
Requires-Dist: coverage; extra == 'test'
Requires-Dist: flake8; extra == 'test'
Requires-Dist: hatch; extra == 'test'
Requires-Dist: isort; extra == 'test'
Requires-Dist: pytest-cov; extra == 'test'
Requires-Dist: pytest-django>=4.8.0; extra == 'test'
Requires-Dist: pytest>=8.2.1; extra == 'test'
Requires-Dist: tox; extra == 'test'
Requires-Dist: twine; extra == 'test'
